<?xml version="1.0" encoding="UTF-8"?>
<Export generator="Cache" version="25">
<Class name="Form.REST.Objects">
<Description>
Брокер работы с индивидуальными объектами</Description>
<Super>Form.REST.Abstract</Super>
<TimeCreated>64090,79332.572705</TimeCreated>

<Parameter name="ALL">
<Default>*</Default>
</Parameter>

<Parameter name="INFO">
<Default>id AS _id, displayName</Default>
</Parameter>

<XData name="UrlMap">
<XMLNamespace>http://www.intersystems.com/urlmap</XMLNamespace>
<Data><![CDATA[
<Routes>
<Route Url="/:form/:query" Method="GET" Call="getFormObjects"/>
</Routes>
]]></Data>
</XData>

<Method name="getFormObjects">
<Description>
Get all form objects</Description>
<ClassMethod>1</ClassMethod>
<FormalSpec>class:%String="",queryType:%String</FormalSpec>
<ReturnType>%Status</ReturnType>
<Implementation><![CDATA[
	#define ClassSQLTable(%c)    ($$$comClassKeyGet(%c,$$$cCLASSsqlschemaname)_"."_$$$comClassKeyGet(%c,$$$cCLASSsqltablename))
	#dim sc As %Status = $$$OK
	set sc = ##class(Form.Info).formExistsStatus(class)
	return:$$$ISERR(sc) sc
	set sc = ..getBaseQuery(queryType, .queryBase)
	return:$$$ISERR(sc) sc	
	
	set table = $$$ClassSQLTable(class)
	set sql = queryBase _ table
	
	set sc = ##class(Form.JSON.SQL).WriteJSONFromSQL(sql, class)
	return sc
]]></Implementation>
</Method>

<Method name="getBaseQuery">
<ClassMethod>1</ClassMethod>
<FormalSpec>queryType:%String,*queryBase:%String</FormalSpec>
<ReturnType>%Status</ReturnType>
<Implementation><![CDATA[
	set queryBase = ""
	#dim sc As %Status = $$$OK
	if ##class(%Dictionary.ParameterDefinition).IDKEYExists($classname(), $ZCVT(queryType, "U")) {
		/// we want only parameters defined in this class
		set queryBase = $parameter(, $ZCVT(queryType, "U"))
	} elseif 0 {
		/// TODO Some other type of "get stuff between SELECT and FROM"
		/// some callback class maybe
	} else {
		set sc = $$$ERROR($$$GeneralError, "Query type " _ queryType _ " not found")		
	}
	
	if (queryBase'="") {
		set queryBase = "SELECT " _ queryBase _ " FROM "
	}
	
	return sc
]]></Implementation>
</Method>
</Class>
</Export>
